{
  "lastExecutionTime": "2026-07-01T09:03:10.293Z",
  "data": [
    {
      "repoName": "tyk-analytics",
      "branch": "master",
      "jobs": [
        {
          "id": 84283544179,
          "name": "ui-tests (redis7, mongo7, sha256, not local and not dind and not nightly, master, $ECR/tyk-pump:m...",
          "status": "completed",
          "conclusion": "success",
          "started_at": "2026-06-30T11:57:10Z",
          "duration": 999000,
          "url": "https://github.com/TykTechnologies/tyk-analytics/actions/runs/28441408942/job/84283544179",
          "head_branch": "master",
          "repo_name": "tyk-analytics",
          "workflow_file": "release.yml"
        },
        {
          "id": 84283553517,
          "name": "api-tests (redis7, mongo7, sha256, not local and not dind and not nightly, master, $ECR/tyk-pump:...",
          "status": "completed",
          "conclusion": "success",
          "started_at": "2026-06-30T11:57:29Z",
          "duration": 2458000,
          "url": "https://github.com/TykTechnologies/tyk-analytics/actions/runs/28441408942/job/84283553517",
          "head_branch": "master",
          "repo_name": "tyk-analytics",
          "workflow_file": "release.yml"
        },
        {
          "id": 84283553537,
          "name": "api-tests (redis6, postgres15, murmur128, not local and not dind and not sql and not nightly, mas...",
          "status": "completed",
          "conclusion": "success",
          "started_at": "2026-06-30T11:57:30Z",
          "duration": 2491000,
          "url": "https://github.com/TykTechnologies/tyk-analytics/actions/runs/28441408942/job/84283553537",
          "head_branch": "master",
          "repo_name": "tyk-analytics",
          "workflow_file": "release.yml"
        },
        {
          "id": 84432676930,
          "name": "api-tests (valkey8, mongo8, murmur128, not local and not dind, master, $ECR/tyk-pump:master, $ECR...",
          "status": "completed",
          "conclusion": "success",
          "started_at": "2026-07-01T00:59:23Z",
          "duration": 2893000,
          "url": "https://github.com/TykTechnologies/tyk-analytics/actions/runs/28486057332/job/84432676930",
          "head_branch": "master",
          "repo_name": "tyk-analytics",
          "workflow_file": "nightly-e2e-tests.yml"
        },
        {
          "id": 84432676934,
          "name": "api-tests (redis7, mongo7, sha256, not local and not dind and not nightly, master, $ECR/tyk-pump:...",
          "status": "completed",
          "conclusion": "success",
          "started_at": "2026-07-01T00:59:26Z",
          "duration": 2466000,
          "url": "https://github.com/TykTechnologies/tyk-analytics/actions/runs/28486057332/job/84432676934",
          "head_branch": "master",
          "repo_name": "tyk-analytics",
          "workflow_file": "nightly-e2e-tests.yml"
        },
        {
          "id": 84432676935,
          "name": "api-tests (redis7, mongo8, murmur128, not local and not dind, release-5.8, $ECR/tyk-sink:release-...",
          "status": "completed",
          "conclusion": "success",
          "started_at": "2026-07-01T00:59:27Z",
          "duration": 1208000,
          "url": "https://github.com/TykTechnologies/tyk-analytics/actions/runs/28486057332/job/84432676935",
          "head_branch": "master",
          "repo_name": "tyk-analytics",
          "workflow_file": "nightly-e2e-tests.yml"
        },
        {
          "id": 84432676939,
          "name": "api-tests (redis6, postgres15, murmur128, not local and not dind and not sql and not nightly, mas...",
          "status": "completed",
          "conclusion": "success",
          "started_at": "2026-07-01T00:59:29Z",
          "duration": 2470000,
          "url": "https://github.com/TykTechnologies/tyk-analytics/actions/runs/28486057332/job/84432676939",
          "head_branch": "master",
          "repo_name": "tyk-analytics",
          "workflow_file": "nightly-e2e-tests.yml"
        },
        {
          "id": 84432676941,
          "name": "api-tests (valkey8, postgres15, sha256, not local and not dind and not sql, master, $ECR/tyk-pump...",
          "status": "completed",
          "conclusion": "success",
          "started_at": "2026-07-01T00:59:28Z",
          "duration": 2895000,
          "url": "https://github.com/TykTechnologies/tyk-analytics/actions/runs/28486057332/job/84432676941",
          "head_branch": "master",
          "repo_name": "tyk-analytics",
          "workflow_file": "nightly-e2e-tests.yml"
        },
        {
          "id": 84432676943,
          "name": "api-tests (redis7, mongo8, murmur128, not local and not dind, release-5.13, $ECR/tyk-sink:release...",
          "status": "completed",
          "conclusion": "success",
          "started_at": "2026-07-01T00:59:29Z",
          "duration": 2557000,
          "url": "https://github.com/TykTechnologies/tyk-analytics/actions/runs/28486057332/job/84432676943",
          "head_branch": "master",
          "repo_name": "tyk-analytics",
          "workflow_file": "nightly-e2e-tests.yml"
        },
        {
          "id": 84432740357,
          "name": "ui-tests (redis7, mongo8, murmur128, not local and not dind, release-5.8, $ECR/tyk-pump:master, $...",
          "status": "completed",
          "conclusion": "success",
          "started_at": "2026-07-01T00:59:31Z",
          "duration": 627000,
          "url": "https://github.com/TykTechnologies/tyk-analytics/actions/runs/28486057332/job/84432740357",
          "head_branch": "master",
          "repo_name": "tyk-analytics",
          "workflow_file": "nightly-e2e-tests.yml"
        },
        {
          "id": 84432740367,
          "name": "ui-tests (redis7, mongo8, murmur128, not local and not dind, release-5.13, $ECR/tyk-pump:master, ...",
          "status": "completed",
          "conclusion": "success",
          "started_at": "2026-07-01T00:59:41Z",
          "duration": 988000,
          "url": "https://github.com/TykTechnologies/tyk-analytics/actions/runs/28486057332/job/84432740367",
          "head_branch": "master",
          "repo_name": "tyk-analytics",
          "workflow_file": "nightly-e2e-tests.yml"
        },
        {
          "id": 84432740372,
          "name": "ui-tests (redis7, mongo7, sha256, not local and not dind and not nightly, master, $ECR/tyk-pump:m...",
          "status": "completed",
          "conclusion": "success",
          "started_at": "2026-07-01T00:59:30Z",
          "duration": 1021000,
          "url": "https://github.com/TykTechnologies/tyk-analytics/actions/runs/28486057332/job/84432740372",
          "head_branch": "master",
          "repo_name": "tyk-analytics",
          "workflow_file": "nightly-e2e-tests.yml"
        },
        {
          "id": 84432740430,
          "name": "ui-tests (valkey8, mongo8, sha256, not local and not dind, master, $ECR/tyk-pump:master, $ECR/tyk...",
          "status": "completed",
          "conclusion": "success",
          "started_at": "2026-07-01T00:59:44Z",
          "duration": 1006000,
          "url": "https://github.com/TykTechnologies/tyk-analytics/actions/runs/28486057332/job/84432740430",
          "head_branch": "master",
          "repo_name": "tyk-analytics",
          "workflow_file": "nightly-e2e-tests.yml"
        },
        {
          "id": 83961007335,
          "name": "k8s-tests (functional, pytest -s -m dash_admin, false, api-test-report, functional-tests-k8s)",
          "status": "completed",
          "conclusion": "success",
          "started_at": "2026-06-29T01:29:27Z",
          "duration": 191000,
          "url": "https://github.com/TykTechnologies/tyk-analytics/actions/runs/28342674646/job/83961007335",
          "head_branch": "master",
          "repo_name": "tyk-analytics",
          "workflow_file": "k8s-api-tests.yaml"
        },
        {
          "id": 83961007349,
          "name": "k8s-tests (resilience, pytest -s -m resilience, true, resilience-test-report, resilience-logs)",
          "status": "completed",
          "conclusion": "success",
          "started_at": "2026-06-29T01:29:39Z",
          "duration": 548000,
          "url": "https://github.com/TykTechnologies/tyk-analytics/actions/runs/28342674646/job/83961007349",
          "head_branch": "master",
          "repo_name": "tyk-analytics",
          "workflow_file": "k8s-api-tests.yaml"
        },
        {
          "id": 84430330800,
          "name": "api-tests (postgres15)",
          "status": "completed",
          "conclusion": "success",
          "started_at": "2026-07-01T00:38:09Z",
          "duration": 129000,
          "url": "https://github.com/TykTechnologies/tyk-analytics/actions/runs/28485296376/job/84430330800",
          "head_branch": "master",
          "repo_name": "tyk-analytics",
          "workflow_file": "upgrade-tests.yml"
        },
        {
          "id": 84430330821,
          "name": "api-tests (mongo7)",
          "status": "completed",
          "conclusion": "success",
          "started_at": "2026-07-01T00:38:10Z",
          "duration": 128000,
          "url": "https://github.com/TykTechnologies/tyk-analytics/actions/runs/28485296376/job/84430330821",
          "head_branch": "master",
          "repo_name": "tyk-analytics",
          "workflow_file": "upgrade-tests.yml"
        }
      ]
    },
    {
      "repoName": "tyk-analytics",
      "branch": "release-5.8",
      "jobs": [
        {
          "id": 84427576425,
          "name": "api-tests (redis7, mongo7, sha256, not local and not dind and not nightly, master, $ECR/tyk-pump:...",
          "status": "completed",
          "conclusion": "failure",
          "started_at": "2026-07-01T00:14:36Z",
          "duration": 1231000,
          "url": "https://github.com/TykTechnologies/tyk-analytics/actions/runs/28443248502/job/84427576425",
          "head_branch": "release-5.8",
          "repo_name": "tyk-analytics",
          "workflow_file": "release.yml"
        },
        {
          "id": 84427576446,
          "name": "api-tests (redis6, postgres15, murmur128, not local and not dind and not sql and not nightly, mas...",
          "status": "completed",
          "conclusion": "success",
          "started_at": "2026-07-01T00:14:37Z",
          "duration": 1188000,
          "url": "https://github.com/TykTechnologies/tyk-analytics/actions/runs/28443248502/job/84427576446",
          "head_branch": "release-5.8",
          "repo_name": "tyk-analytics",
          "workflow_file": "release.yml"
        },
        {
          "id": 84427598935,
          "name": "ui-tests (redis7, mongo7, sha256, not local and not dind and not nightly, master, $ECR/tyk-pump:m...",
          "status": "completed",
          "conclusion": "success",
          "started_at": "2026-07-01T00:15:08Z",
          "duration": 637000,
          "url": "https://github.com/TykTechnologies/tyk-analytics/actions/runs/28443248502/job/84427598935",
          "head_branch": "release-5.8",
          "repo_name": "tyk-analytics",
          "workflow_file": "release.yml"
        }
      ]
    },
    {
      "repoName": "tyk-analytics",
      "branch": "release-5.13",
      "jobs": [
        {
          "id": 84436629996,
          "name": "api-tests (redis6, postgres15, murmur128, not local and not dind and not sql and not nightly, mas...",
          "status": "completed",
          "conclusion": "success",
          "started_at": "2026-07-01T01:33:57Z",
          "duration": 2142000,
          "url": "https://github.com/TykTechnologies/tyk-analytics/actions/runs/28483996946/job/84436629996",
          "head_branch": "release-5.13",
          "repo_name": "tyk-analytics",
          "workflow_file": "release.yml"
        },
        {
          "id": 84436630003,
          "name": "api-tests (redis7, mongo7, sha256, not local and not dind and not nightly, master, $ECR/tyk-pump:...",
          "status": "completed",
          "conclusion": "success",
          "started_at": "2026-07-01T01:33:55Z",
          "duration": 2124000,
          "url": "https://github.com/TykTechnologies/tyk-analytics/actions/runs/28483996946/job/84436630003",
          "head_branch": "release-5.13",
          "repo_name": "tyk-analytics",
          "workflow_file": "release.yml"
        },
        {
          "id": 84436630684,
          "name": "ui-tests (redis7, mongo7, sha256, not local and not dind and not nightly, master, $ECR/tyk-pump:m...",
          "status": "completed",
          "conclusion": "success",
          "started_at": "2026-07-01T01:33:59Z",
          "duration": 955000,
          "url": "https://github.com/TykTechnologies/tyk-analytics/actions/runs/28483996946/job/84436630684",
          "head_branch": "release-5.13",
          "repo_name": "tyk-analytics",
          "workflow_file": "release.yml"
        }
      ]
    },
    {
      "repoName": "tyk-analytics-ui",
      "branch": "master",
      "jobs": [
        {
          "id": 83957046207,
          "name": "ui-test (1.21, 24.15.0, postgres15, murmur128, redis6, 1.21-bullseye)",
          "status": "completed",
          "conclusion": "success",
          "started_at": "2026-06-29T00:40:45Z",
          "duration": 2349000,
          "url": "https://github.com/TykTechnologies/tyk-analytics-ui/actions/runs/28341610056/job/83957046207",
          "head_branch": "master",
          "repo_name": "tyk-analytics-ui",
          "workflow_file": "ui-tests.yml"
        },
        {
          "id": 83957046209,
          "name": "ui-test (1.21, 24.15.0, mongo44, murmur128, redis6, 1.21-bullseye)",
          "status": "completed",
          "conclusion": "success",
          "started_at": "2026-06-29T00:40:46Z",
          "duration": 2319000,
          "url": "https://github.com/TykTechnologies/tyk-analytics-ui/actions/runs/28341610056/job/83957046209",
          "head_branch": "master",
          "repo_name": "tyk-analytics-ui",
          "workflow_file": "ui-tests.yml"
        }
      ]
    },
    {
      "repoName": "tyk",
      "branch": "master",
      "jobs": [
        {
          "id": 84228996336,
          "name": "api-tests (redis6, postgres15, murmur128, not local and not dind and not sql and not nightly, mas...",
          "status": "completed",
          "conclusion": "success",
          "started_at": "2026-06-30T06:51:31Z",
          "duration": 2472000,
          "url": "https://github.com/TykTechnologies/tyk/actions/runs/28424447771/job/84228996336",
          "head_branch": "master",
          "repo_name": "tyk",
          "workflow_file": "release.yml"
        },
        {
          "id": 84228996351,
          "name": "api-tests (redis7, mongo7, sha256, not local and not dind and not nightly, master, $ECR/tyk-pump:...",
          "status": "completed",
          "conclusion": "success",
          "started_at": "2026-06-30T06:51:47Z",
          "duration": 2459000,
          "url": "https://github.com/TykTechnologies/tyk/actions/runs/28424447771/job/84228996351",
          "head_branch": "master",
          "repo_name": "tyk",
          "workflow_file": "release.yml"
        }
      ]
    },
    {
      "repoName": "tyk",
      "branch": "release-5.8",
      "jobs": [
        {
          "id": 84287107574,
          "name": "api-tests (redis6, postgres15, murmur128, not local and not dind and not sql and not nightly, mas...",
          "status": "completed",
          "conclusion": "success",
          "started_at": "2026-06-30T12:16:12Z",
          "duration": 1176000,
          "url": "https://github.com/TykTechnologies/tyk/actions/runs/28443196297/job/84287107574",
          "head_branch": "release-5.8",
          "repo_name": "tyk",
          "workflow_file": "release.yml"
        },
        {
          "id": 84287107593,
          "name": "api-tests (redis7, mongo7, sha256, not local and not dind and not nightly, master, $ECR/tyk-pump:...",
          "status": "completed",
          "conclusion": "success",
          "started_at": "2026-06-30T12:16:25Z",
          "duration": 1213000,
          "url": "https://github.com/TykTechnologies/tyk/actions/runs/28443196297/job/84287107593",
          "head_branch": "release-5.8",
          "repo_name": "tyk",
          "workflow_file": "release.yml"
        }
      ]
    },
    {
      "repoName": "tyk",
      "branch": "release-5.13",
      "jobs": [
        {
          "id": 84434141040,
          "name": "api-tests (redis7, mongo7, sha256, not local and not dind and not nightly, master, $ECR/tyk-pump:...",
          "status": "completed",
          "conclusion": "success",
          "started_at": "2026-07-01T01:11:37Z",
          "duration": 2139000,
          "url": "https://github.com/TykTechnologies/tyk/actions/runs/28448313847/job/84434141040",
          "head_branch": "release-5.13",
          "repo_name": "tyk",
          "workflow_file": "release.yml"
        },
        {
          "id": 84434141046,
          "name": "api-tests (redis6, postgres15, murmur128, not local and not dind and not sql and not nightly, mas...",
          "status": "completed",
          "conclusion": "success",
          "started_at": "2026-07-01T01:11:36Z",
          "duration": 2126000,
          "url": "https://github.com/TykTechnologies/tyk/actions/runs/28448313847/job/84434141046",
          "head_branch": "release-5.13",
          "repo_name": "tyk",
          "workflow_file": "release.yml"
        }
      ]
    },
    {
      "repoName": "tyk-sink",
      "branch": "master",
      "jobs": [
        {
          "id": 84245371919,
          "name": "api-tests (redis7, mongo7, sha256, not local and not dind and not nightly, master, $ECR/tyk-pump:...",
          "status": "completed",
          "conclusion": "success",
          "started_at": "2026-06-30T08:29:15Z",
          "duration": 2449000,
          "url": "https://github.com/TykTechnologies/tyk-sink/actions/runs/28430807425/job/84245371919",
          "head_branch": "master",
          "repo_name": "tyk-sink",
          "workflow_file": "release.yml"
        },
        {
          "id": 84245371927,
          "name": "api-tests (redis6, postgres15, murmur128, not local and not dind and not sql and not nightly, mas...",
          "status": "completed",
          "conclusion": "success",
          "started_at": "2026-06-30T08:29:16Z",
          "duration": 2442000,
          "url": "https://github.com/TykTechnologies/tyk-sink/actions/runs/28430807425/job/84245371927",
          "head_branch": "master",
          "repo_name": "tyk-sink",
          "workflow_file": "release.yml"
        }
      ]
    },
    {
      "repoName": "tyk-pump",
      "branch": "master",
      "jobs": [
        {
          "id": 84264204211,
          "name": "api-tests (redis6, postgres15, murmur128, not local and not dind and not sql and not nightly, mas...",
          "status": "completed",
          "conclusion": "success",
          "started_at": "2026-06-30T10:10:17Z",
          "duration": 2501000,
          "url": "https://github.com/TykTechnologies/tyk-pump/actions/runs/28436406518/job/84264204211",
          "head_branch": "master",
          "repo_name": "tyk-pump",
          "workflow_file": "release.yml"
        },
        {
          "id": 84264204296,
          "name": "api-tests (redis7, mongo7, sha256, not local and not dind and not nightly, master, $ECR/tyk-sink:...",
          "status": "completed",
          "conclusion": "success",
          "started_at": "2026-06-30T10:10:19Z",
          "duration": 2509000,
          "url": "https://github.com/TykTechnologies/tyk-pump/actions/runs/28436406518/job/84264204296",
          "head_branch": "master",
          "repo_name": "tyk-pump",
          "workflow_file": "release.yml"
        }
      ]
    },
    {
      "repoName": "portal",
      "branch": "master",
      "jobs": [
        {
          "id": 82975776463,
          "name": "test (1.25, amd64, 18.16)",
          "status": "completed",
          "conclusion": "success",
          "started_at": "2026-06-23T14:06:34Z",
          "duration": 160000,
          "url": "https://github.com/TykTechnologies/portal/actions/runs/28032241758/job/82975776463",
          "head_branch": "master",
          "repo_name": "portal",
          "workflow_file": "api_tests.yml"
        },
        {
          "id": 82975776069,
          "name": "test (1.25, amd64, 18.16)",
          "status": "completed",
          "conclusion": "success",
          "started_at": "2026-06-23T14:06:30Z",
          "duration": 2237000,
          "url": "https://github.com/TykTechnologies/portal/actions/runs/28032241491/job/82975776069",
          "head_branch": "master",
          "repo_name": "portal",
          "workflow_file": "ui_tests_postgres.yml"
        }
      ]
    }
  ]
}