{
  "lastExecutionTime": "2026-07-17T05:52:24.342Z",
  "data": [
    {
      "repoName": "tyk-analytics",
      "branch": "master",
      "jobs": [
        {
          "id": 87814991126,
          "name": "ui-tests (redis7, mongo7, sha256, not local and not dind and not nightly, master, $ECR/tyk-pump:m...",
          "status": "in_progress",
          "conclusion": null,
          "started_at": "2026-07-17T05:48:13Z",
          "duration": -1784267293000,
          "url": "https://github.com/TykTechnologies/tyk-analytics/actions/runs/29557726747/job/87814991126",
          "head_branch": "master",
          "repo_name": "tyk-analytics",
          "workflow_file": "release.yml"
        },
        {
          "id": 87815046721,
          "name": "api-tests (valkey9_1, postgres15, murmur128, not local and not dind and not sql and not nightly, ...",
          "status": "in_progress",
          "conclusion": null,
          "started_at": "2026-07-17T05:48:22Z",
          "duration": -1784267302000,
          "url": "https://github.com/TykTechnologies/tyk-analytics/actions/runs/29557726747/job/87815046721",
          "head_branch": "master",
          "repo_name": "tyk-analytics",
          "workflow_file": "release.yml"
        },
        {
          "id": 87815046729,
          "name": "api-tests (redis7, mongo7, sha256, not local and not dind and not nightly, master, $ECR/tyk-pump:...",
          "status": "in_progress",
          "conclusion": null,
          "started_at": "2026-07-17T05:48:23Z",
          "duration": -1784267303000,
          "url": "https://github.com/TykTechnologies/tyk-analytics/actions/runs/29557726747/job/87815046729",
          "head_branch": "master",
          "repo_name": "tyk-analytics",
          "workflow_file": "release.yml"
        },
        {
          "id": 87776330045,
          "name": "ui-tests (valkey8, postgres15, murmur128, release-5.13, $ECR/tyk-pump:master, $ECR/tyk-sink:master)",
          "status": "completed",
          "conclusion": "success",
          "started_at": "2026-07-17T00:39:08Z",
          "duration": 928000,
          "url": "https://github.com/TykTechnologies/tyk-analytics/actions/runs/29545334781/job/87776330045",
          "head_branch": "master",
          "repo_name": "tyk-analytics",
          "workflow_file": "nightly-e2e-tests.yml"
        },
        {
          "id": 87776330076,
          "name": "ui-tests (redis8_4, postgres17, sha256, master, $ECR/tyk-pump:master, $ECR/tyk-sink:master, $ECR/...",
          "status": "completed",
          "conclusion": "success",
          "started_at": "2026-07-17T00:39:09Z",
          "duration": 1015000,
          "url": "https://github.com/TykTechnologies/tyk-analytics/actions/runs/29545334781/job/87776330076",
          "head_branch": "master",
          "repo_name": "tyk-analytics",
          "workflow_file": "nightly-e2e-tests.yml"
        },
        {
          "id": 87776330104,
          "name": "ui-tests (redis7, mongo7, sha256, not local and not dind and not nightly, master, $ECR/tyk-pump:m...",
          "status": "completed",
          "conclusion": "success",
          "started_at": "2026-07-17T00:39:09Z",
          "duration": 1023000,
          "url": "https://github.com/TykTechnologies/tyk-analytics/actions/runs/29545334781/job/87776330104",
          "head_branch": "master",
          "repo_name": "tyk-analytics",
          "workflow_file": "nightly-e2e-tests.yml"
        },
        {
          "id": 87776330141,
          "name": "ui-tests (redis7, mongo8, murmur128, release-5.8, $ECR/tyk-pump:master, $ECR/tyk-sink:master)",
          "status": "completed",
          "conclusion": "failure",
          "started_at": "2026-07-17T00:39:10Z",
          "duration": 675000,
          "url": "https://github.com/TykTechnologies/tyk-analytics/actions/runs/29545334781/job/87776330141",
          "head_branch": "master",
          "repo_name": "tyk-analytics",
          "workflow_file": "nightly-e2e-tests.yml"
        },
        {
          "id": 87776330443,
          "name": "api-tests (valkey8_1, postgres17, murmur128, not local and not dind and not sql, master, $ECR/tyk...",
          "status": "completed",
          "conclusion": "success",
          "started_at": "2026-07-17T00:39:11Z",
          "duration": 2872000,
          "url": "https://github.com/TykTechnologies/tyk-analytics/actions/runs/29545334781/job/87776330443",
          "head_branch": "master",
          "repo_name": "tyk-analytics",
          "workflow_file": "nightly-e2e-tests.yml"
        },
        {
          "id": 87776330461,
          "name": "api-tests (redis8_2, mongo8, murmur128, not local and not dind, release-5.13, $ECR/tyk-pump:maste...",
          "status": "completed",
          "conclusion": "success",
          "started_at": "2026-07-17T00:39:11Z",
          "duration": 2563000,
          "url": "https://github.com/TykTechnologies/tyk-analytics/actions/runs/29545334781/job/87776330461",
          "head_branch": "master",
          "repo_name": "tyk-analytics",
          "workflow_file": "nightly-e2e-tests.yml"
        },
        {
          "id": 87776330465,
          "name": "api-tests (redis8, postgres15, sha256, not local and not dind and not sql, master, $ECR/tyk-pump:...",
          "status": "completed",
          "conclusion": "success",
          "started_at": "2026-07-17T00:39:31Z",
          "duration": 2884000,
          "url": "https://github.com/TykTechnologies/tyk-analytics/actions/runs/29545334781/job/87776330465",
          "head_branch": "master",
          "repo_name": "tyk-analytics",
          "workflow_file": "nightly-e2e-tests.yml"
        },
        {
          "id": 87776330479,
          "name": "api-tests (valkey7_2, postgres16, sha256, not local and not dind and not sql, release-5.8, $ECR/t...",
          "status": "completed",
          "conclusion": "failure",
          "started_at": "2026-07-17T00:39:27Z",
          "duration": 247000,
          "url": "https://github.com/TykTechnologies/tyk-analytics/actions/runs/29545334781/job/87776330479",
          "head_branch": "master",
          "repo_name": "tyk-analytics",
          "workflow_file": "nightly-e2e-tests.yml"
        },
        {
          "id": 87776330522,
          "name": "api-tests (redis8_4, postgres17, murmur128, not local and not dind and not sql, master, $ECR/tyk-...",
          "status": "completed",
          "conclusion": "success",
          "started_at": "2026-07-17T00:39:30Z",
          "duration": 2870000,
          "url": "https://github.com/TykTechnologies/tyk-analytics/actions/runs/29545334781/job/87776330522",
          "head_branch": "master",
          "repo_name": "tyk-analytics",
          "workflow_file": "nightly-e2e-tests.yml"
        },
        {
          "id": 87776330539,
          "name": "api-tests (valkey9_1, postgres15, murmur128, not local and not dind and not sql and not nightly, ...",
          "status": "completed",
          "conclusion": "success",
          "started_at": "2026-07-17T00:39:31Z",
          "duration": 2450000,
          "url": "https://github.com/TykTechnologies/tyk-analytics/actions/runs/29545334781/job/87776330539",
          "head_branch": "master",
          "repo_name": "tyk-analytics",
          "workflow_file": "nightly-e2e-tests.yml"
        },
        {
          "id": 87776330545,
          "name": "api-tests (valkey8, mongo8, sha256, not local and not dind, master, $ECR/tyk-pump:master, $ECR/ty...",
          "status": "completed",
          "conclusion": "success",
          "started_at": "2026-07-17T00:39:31Z",
          "duration": 2892000,
          "url": "https://github.com/TykTechnologies/tyk-analytics/actions/runs/29545334781/job/87776330545",
          "head_branch": "master",
          "repo_name": "tyk-analytics",
          "workflow_file": "nightly-e2e-tests.yml"
        },
        {
          "id": 87776330546,
          "name": "api-tests (redis7, mongo7, sha256, not local and not dind and not nightly, master, $ECR/tyk-pump:...",
          "status": "completed",
          "conclusion": "success",
          "started_at": "2026-07-17T00:39:32Z",
          "duration": 2444000,
          "url": "https://github.com/TykTechnologies/tyk-analytics/actions/runs/29545334781/job/87776330546",
          "head_branch": "master",
          "repo_name": "tyk-analytics",
          "workflow_file": "nightly-e2e-tests.yml"
        },
        {
          "id": 87510446440,
          "name": "k8s-tests (release-5.13, resilience, pytest -s -m resilience, true, resilience-test-report, resil...",
          "status": "completed",
          "conclusion": "failure",
          "started_at": "2026-07-16T01:02:03Z",
          "duration": 341000,
          "url": "https://github.com/TykTechnologies/tyk-analytics/actions/runs/29462379611/job/87510446440",
          "head_branch": "master",
          "repo_name": "tyk-analytics",
          "workflow_file": "k8s-api-tests.yaml"
        },
        {
          "id": 87510446463,
          "name": "k8s-tests (master, functional, pytest -s -m dash_admin, false, api-test-report, functional-tests-...",
          "status": "completed",
          "conclusion": "success",
          "started_at": "2026-07-16T01:02:51Z",
          "duration": 194000,
          "url": "https://github.com/TykTechnologies/tyk-analytics/actions/runs/29462379611/job/87510446463",
          "head_branch": "master",
          "repo_name": "tyk-analytics",
          "workflow_file": "k8s-api-tests.yaml"
        },
        {
          "id": 87510446471,
          "name": "k8s-tests (master, resilience, pytest -s -m resilience, true, resilience-test-report, resilience-...",
          "status": "completed",
          "conclusion": "failure",
          "started_at": "2026-07-16T01:02:40Z",
          "duration": 460000,
          "url": "https://github.com/TykTechnologies/tyk-analytics/actions/runs/29462379611/job/87510446471",
          "head_branch": "master",
          "repo_name": "tyk-analytics",
          "workflow_file": "k8s-api-tests.yaml"
        },
        {
          "id": 87510446478,
          "name": "k8s-tests (release-5.8, resilience, pytest -s -m resilience, true, resilience-test-report, resili...",
          "status": "completed",
          "conclusion": "failure",
          "started_at": "2026-07-16T01:02:35Z",
          "duration": 437000,
          "url": "https://github.com/TykTechnologies/tyk-analytics/actions/runs/29462379611/job/87510446478",
          "head_branch": "master",
          "repo_name": "tyk-analytics",
          "workflow_file": "k8s-api-tests.yaml"
        },
        {
          "id": 87510446479,
          "name": "k8s-tests (release-5.13, functional, pytest -s -m dash_admin, false, api-test-report, functional-...",
          "status": "completed",
          "conclusion": "success",
          "started_at": "2026-07-16T01:02:17Z",
          "duration": 214000,
          "url": "https://github.com/TykTechnologies/tyk-analytics/actions/runs/29462379611/job/87510446479",
          "head_branch": "master",
          "repo_name": "tyk-analytics",
          "workflow_file": "k8s-api-tests.yaml"
        },
        {
          "id": 87510446487,
          "name": "k8s-tests (release-5.8, functional, pytest -s -m dash_admin, false, api-test-report, functional-t...",
          "status": "completed",
          "conclusion": "success",
          "started_at": "2026-07-16T01:02:50Z",
          "duration": 177000,
          "url": "https://github.com/TykTechnologies/tyk-analytics/actions/runs/29462379611/job/87510446487",
          "head_branch": "master",
          "repo_name": "tyk-analytics",
          "workflow_file": "k8s-api-tests.yaml"
        },
        {
          "id": 87237762016,
          "name": "api-tests (postgres15)",
          "status": "completed",
          "conclusion": "success",
          "started_at": "2026-07-15T00:21:34Z",
          "duration": 142000,
          "url": "https://github.com/TykTechnologies/tyk-analytics/actions/runs/29378808555/job/87237762016",
          "head_branch": "master",
          "repo_name": "tyk-analytics",
          "workflow_file": "upgrade-tests.yml"
        },
        {
          "id": 87237762068,
          "name": "api-tests (mongo7)",
          "status": "completed",
          "conclusion": "success",
          "started_at": "2026-07-15T00:21:35Z",
          "duration": 136000,
          "url": "https://github.com/TykTechnologies/tyk-analytics/actions/runs/29378808555/job/87237762068",
          "head_branch": "master",
          "repo_name": "tyk-analytics",
          "workflow_file": "upgrade-tests.yml"
        }
      ]
    },
    {
      "repoName": "tyk-analytics",
      "branch": "release-5.8",
      "jobs": [
        {
          "id": 86337773208,
          "name": "api-tests (redis7, mongo7, sha256, not local and not dind and not nightly, master, $ECR/tyk-pump:...",
          "status": "completed",
          "conclusion": "failure",
          "started_at": "2026-07-10T10:09:24Z",
          "duration": 1100000,
          "url": "https://github.com/TykTechnologies/tyk-analytics/actions/runs/29084691559/job/86337773208",
          "head_branch": "release-5.8",
          "repo_name": "tyk-analytics",
          "workflow_file": "release.yml"
        },
        {
          "id": 86337773244,
          "name": "api-tests (valkey8_1, postgres15, murmur128, not local and not dind and not sql and not nightly, ...",
          "status": "completed",
          "conclusion": "failure",
          "started_at": "2026-07-10T10:09:20Z",
          "duration": 779000,
          "url": "https://github.com/TykTechnologies/tyk-analytics/actions/runs/29084691559/job/86337773244",
          "head_branch": "release-5.8",
          "repo_name": "tyk-analytics",
          "workflow_file": "release.yml"
        },
        {
          "id": 86337810533,
          "name": "ui-tests (redis7, mongo7, sha256, not local and not dind and not nightly, master, $ECR/tyk-pump:m...",
          "status": "completed",
          "conclusion": "success",
          "started_at": "2026-07-10T10:09:27Z",
          "duration": 613000,
          "url": "https://github.com/TykTechnologies/tyk-analytics/actions/runs/29084691559/job/86337810533",
          "head_branch": "release-5.8",
          "repo_name": "tyk-analytics",
          "workflow_file": "release.yml"
        }
      ]
    },
    {
      "repoName": "tyk-analytics",
      "branch": "release-5.13",
      "jobs": [
        {
          "id": 87317908622,
          "name": "api-tests (valkey8_1, postgres15, murmur128, not local and not dind and not sql and not nightly, ...",
          "status": "completed",
          "conclusion": "success",
          "started_at": "2026-07-15T09:33:28Z",
          "duration": 2134000,
          "url": "https://github.com/TykTechnologies/tyk-analytics/actions/runs/29402966874/job/87317908622",
          "head_branch": "release-5.13",
          "repo_name": "tyk-analytics",
          "workflow_file": "release.yml"
        },
        {
          "id": 87317908682,
          "name": "api-tests (redis7, mongo7, sha256, not local and not dind and not nightly, master, $ECR/tyk-pump:...",
          "status": "completed",
          "conclusion": "success",
          "started_at": "2026-07-15T09:33:29Z",
          "duration": 2133000,
          "url": "https://github.com/TykTechnologies/tyk-analytics/actions/runs/29402966874/job/87317908682",
          "head_branch": "release-5.13",
          "repo_name": "tyk-analytics",
          "workflow_file": "release.yml"
        },
        {
          "id": 87317981864,
          "name": "ui-tests (redis7, mongo7, sha256, not local and not dind and not nightly, master, $ECR/tyk-pump:m...",
          "status": "completed",
          "conclusion": "failure",
          "started_at": "2026-07-15T09:33:36Z",
          "duration": 970000,
          "url": "https://github.com/TykTechnologies/tyk-analytics/actions/runs/29402966874/job/87317981864",
          "head_branch": "release-5.13",
          "repo_name": "tyk-analytics",
          "workflow_file": "release.yml"
        }
      ]
    },
    {
      "repoName": "tyk-analytics-ui",
      "branch": "master",
      "jobs": [
        {
          "id": 87505587360,
          "name": "ui-test (1.21, 24.15.0, mongo44, murmur128, redis6, 1.21-bullseye)",
          "status": "completed",
          "conclusion": "success",
          "started_at": "2026-07-16T00:26:43Z",
          "duration": 2316000,
          "url": "https://github.com/TykTechnologies/tyk-analytics-ui/actions/runs/29461438881/job/87505587360",
          "head_branch": "master",
          "repo_name": "tyk-analytics-ui",
          "workflow_file": "ui-tests.yml"
        },
        {
          "id": 87505587385,
          "name": "ui-test (1.21, 24.15.0, postgres15, murmur128, redis6, 1.21-bullseye)",
          "status": "completed",
          "conclusion": "success",
          "started_at": "2026-07-16T00:26:43Z",
          "duration": 2318000,
          "url": "https://github.com/TykTechnologies/tyk-analytics-ui/actions/runs/29461438881/job/87505587385",
          "head_branch": "master",
          "repo_name": "tyk-analytics-ui",
          "workflow_file": "ui-tests.yml"
        }
      ]
    },
    {
      "repoName": "tyk",
      "branch": "master",
      "jobs": [
        {
          "id": 87155954752,
          "name": "api-tests (redis7, mongo7, sha256, not local and not dind and not nightly, master, $ECR/tyk-pump:...",
          "status": "completed",
          "conclusion": "failure",
          "started_at": "2026-07-14T17:25:36Z",
          "duration": 2625000,
          "url": "https://github.com/TykTechnologies/tyk/actions/runs/29351636448/job/87155954752",
          "head_branch": "master",
          "repo_name": "tyk",
          "workflow_file": "release.yml"
        },
        {
          "id": 87155954763,
          "name": "api-tests (valkey9_1, postgres15, murmur128, not local and not dind and not sql and not nightly, ...",
          "status": "completed",
          "conclusion": "success",
          "started_at": "2026-07-14T17:25:36Z",
          "duration": 2455000,
          "url": "https://github.com/TykTechnologies/tyk/actions/runs/29351636448/job/87155954763",
          "head_branch": "master",
          "repo_name": "tyk",
          "workflow_file": "release.yml"
        }
      ]
    },
    {
      "repoName": "tyk",
      "branch": "release-5.8",
      "jobs": [
        {
          "id": 86337119561,
          "name": "api-tests (valkey8_1, postgres15, murmur128, not local and not dind and not sql and not nightly, ...",
          "status": "completed",
          "conclusion": "success",
          "started_at": "2026-07-10T10:05:14Z",
          "duration": 1186000,
          "url": "https://github.com/TykTechnologies/tyk/actions/runs/29084622188/job/86337119561",
          "head_branch": "release-5.8",
          "repo_name": "tyk",
          "workflow_file": "release.yml"
        },
        {
          "id": 86337119563,
          "name": "api-tests (redis7, mongo7, sha256, not local and not dind and not nightly, master, $ECR/tyk-pump:...",
          "status": "completed",
          "conclusion": "success",
          "started_at": "2026-07-10T10:05:14Z",
          "duration": 1217000,
          "url": "https://github.com/TykTechnologies/tyk/actions/runs/29084622188/job/86337119563",
          "head_branch": "release-5.8",
          "repo_name": "tyk",
          "workflow_file": "release.yml"
        }
      ]
    },
    {
      "repoName": "tyk",
      "branch": "release-5.13",
      "jobs": [
        {
          "id": 87317419757,
          "name": "api-tests (redis7, mongo7, sha256, not local and not dind and not nightly, master, $ECR/tyk-pump:...",
          "status": "completed",
          "conclusion": "success",
          "started_at": "2026-07-15T09:30:49Z",
          "duration": 2132000,
          "url": "https://github.com/TykTechnologies/tyk/actions/runs/29402877024/job/87317419757",
          "head_branch": "release-5.13",
          "repo_name": "tyk",
          "workflow_file": "release.yml"
        },
        {
          "id": 87317419809,
          "name": "api-tests (valkey8_1, postgres15, murmur128, not local and not dind and not sql and not nightly, ...",
          "status": "completed",
          "conclusion": "failure",
          "started_at": "2026-07-15T09:30:59Z",
          "duration": 1928000,
          "url": "https://github.com/TykTechnologies/tyk/actions/runs/29402877024/job/87317419809",
          "head_branch": "release-5.13",
          "repo_name": "tyk",
          "workflow_file": "release.yml"
        }
      ]
    },
    {
      "repoName": "tyk-sink",
      "branch": "master",
      "jobs": [
        {
          "id": 87151283920,
          "name": "api-tests (valkey9_1, postgres15, murmur128, not local and not dind and not sql and not nightly, ...",
          "status": "completed",
          "conclusion": "success",
          "started_at": "2026-07-14T17:05:23Z",
          "duration": 2460000,
          "url": "https://github.com/TykTechnologies/tyk-sink/actions/runs/29351776043/job/87151283920",
          "head_branch": "master",
          "repo_name": "tyk-sink",
          "workflow_file": "release.yml"
        },
        {
          "id": 87151283956,
          "name": "api-tests (redis7, mongo7, sha256, not local and not dind and not nightly, master, $ECR/tyk-pump:...",
          "status": "completed",
          "conclusion": "success",
          "started_at": "2026-07-14T17:05:22Z",
          "duration": 2447000,
          "url": "https://github.com/TykTechnologies/tyk-sink/actions/runs/29351776043/job/87151283956",
          "head_branch": "master",
          "repo_name": "tyk-sink",
          "workflow_file": "release.yml"
        }
      ]
    },
    {
      "repoName": "tyk-pump",
      "branch": "master",
      "jobs": [
        {
          "id": 87050206338,
          "name": "api-tests (valkey9_1, postgres15, murmur128, not local and not dind and not sql and not nightly, ...",
          "status": "completed",
          "conclusion": "success",
          "started_at": "2026-07-14T09:36:01Z",
          "duration": 2434000,
          "url": "https://github.com/TykTechnologies/tyk-pump/actions/runs/29322000160/job/87050206338",
          "head_branch": "master",
          "repo_name": "tyk-pump",
          "workflow_file": "release.yml"
        },
        {
          "id": 87050206376,
          "name": "api-tests (redis7, mongo7, sha256, not local and not dind and not nightly, master, $ECR/tyk-pump:...",
          "status": "completed",
          "conclusion": "success",
          "started_at": "2026-07-14T09:36:01Z",
          "duration": 2451000,
          "url": "https://github.com/TykTechnologies/tyk-pump/actions/runs/29322000160/job/87050206376",
          "head_branch": "master",
          "repo_name": "tyk-pump",
          "workflow_file": "release.yml"
        }
      ]
    },
    {
      "repoName": "portal",
      "branch": "master",
      "jobs": [
        {
          "id": 87648333599,
          "name": "test (1.25, amd64, 18.16)",
          "status": "completed",
          "conclusion": "success",
          "started_at": "2026-07-16T14:24:42Z",
          "duration": 155000,
          "url": "https://github.com/TykTechnologies/portal/actions/runs/29506449770/job/87648333599",
          "head_branch": "master",
          "repo_name": "portal",
          "workflow_file": "api_tests.yml"
        },
        {
          "id": 87648344205,
          "name": "test (1.25, amd64, 18.16)",
          "status": "completed",
          "conclusion": "success",
          "started_at": "2026-07-16T14:24:48Z",
          "duration": 1902000,
          "url": "https://github.com/TykTechnologies/portal/actions/runs/29506452959/job/87648344205",
          "head_branch": "master",
          "repo_name": "portal",
          "workflow_file": "ui_tests_postgres.yml"
        }
      ]
    }
  ]
}